Metadata-Version: 2.2
Name: pytest-adaptavist-fixed
Version: 0.30.2
Summary: pytest plugin for generating test execution results within Jira Test Management (tm4j)
Home-page: https://github.com/slug85/pytest-adaptavist
Keywords: python pytest adaptavist kanoah tm4j jira test testmanagement report
Platform: any
Classifier: Framework :: Pytest
Classifier: Intended Audience :: Developers
Classifier: License :: OSI Approved :: MIT License
Classifier: Operating System :: OS Independent
Classifier: Programming Language :: Python
Classifier: Programming Language :: Python :: 3
Classifier: Topic :: Software Development :: Quality Assurance
Classifier: Topic :: Software Development :: Testing
Classifier: Topic :: Utilities
Classifier: Topic :: Software Development :: Libraries :: Python Modules
Requires-Python: >=3.8
License-File: LICENSE.md
Requires-Dist: adaptavist-fixed==0.4
Requires-Dist: pytest>=5.4.0
Requires-Dist: pytest-assume>=2.3.2
Requires-Dist: pytest-metadata>=1.6.0
Provides-Extra: test
Requires-Dist: beautifulsoup4; extra == "test"
Requires-Dist: lxml; extra == "test"
Requires-Dist: requests; extra == "test"
Dynamic: classifier
Dynamic: description
Dynamic: description-content-type
Dynamic: home-page
Dynamic: keywords
Dynamic: platform
Dynamic: provides-extra
Dynamic: requires-dist
Dynamic: requires-python
Dynamic: summary
